bxml/__init__.py
bxml/builder.py
bxml/docx.py
bxml/element_maker.py
bxml/entities.json
bxml/jpath.py
bxml/rng.py
bxml/schema.py
bxml/xlsx.py
bxml/xml.py
bxml/xslt.py
bxml/xt.py
bxml/jars/isorelax.jar
bxml/jars/jing.jar
bxml/jars/saxon.jar
bxml/jars/trang.jar
bxml/jars/xercesImpl.jar
bxml/jars/xml-apis.jar
bxml/jars/saxon9/saxon9-test.jar
bxml/jars/saxon9/saxon9-xqj.jar
bxml/jars/saxon9/saxon9he.jar
bxml/schematron/trunk/schematron/code/iso_abstract_expand.xsl
bxml/schematron/trunk/schematron/code/iso_dsdl_include.xsl
bxml/schematron/trunk/schematron/code/iso_schematron_message.xsl
bxml/schematron/trunk/schematron/code/iso_schematron_message_xslt2.xsl
bxml/schematron/trunk/schematron/code/iso_schematron_skeleton_for_saxon.xsl
bxml/schematron/trunk/schematron/code/iso_schematron_skeleton_for_xslt1.xsl
bxml/schematron/trunk/schematron/code/iso_svrl_for_xslt1.xsl
bxml/schematron/trunk/schematron/code/iso_svrl_for_xslt2.xsl
bxml/xslts/rng2md.xslt
bxml/xslts/rng2sch.xslt
bxml-2.6.1.dist-info/LICENSE
bxml-2.6.1.dist-info/METADATA
bxml-2.6.1.dist-info/WHEEL
bxml-2.6.1.dist-info/top_level.txt
bxml-2.6.1.dist-info/RECORD
